{
  "type": "FeatureCollection",
  "metadata": {
    "generated": 1772004541000,
    "url": "https://earthquake.usgs.gov/earthquakes/feed/v1.0/summary/all_hour.geojson",
    "title": "USGS All Earthquakes, Past Hour",
    "status": 200,
    "api": "2.3.0",
    "count": 5
  },
  "features": [
    {
      "type": "Feature",
      "properties": {
        "mag": 2.1,
        "place": "19 km WSW of Volcano, Hawaii",
        "time": 1772003950000,
        "updated": 1772004189270,
        "tz": null,
        "url": "https://earthquake.usgs.gov/earthquakes/eventpage/hv74908306",
        "detail": "https://earthquake.usgs.gov/earthquakes/feed/v1.0/detail/hv74908306.geojson",
        "felt": null,
        "cdi": null,
        "mmi": null,
        "alert": null,
        "status": "automatic",
        "tsunami": 0,
        "sig": 68,
        "net": "hv",
        "code": "74908306",
        "ids": ",hv74908306,",
        "sources": ",hv,",
        "types": ",origin,phase-data,",
        "nst": 46,
        "dmin": 0.04858,
        "rms": 0.140000001,
        "gap": 36,
        "magType": "md",
        "type": "earthquake",
        "title": "M 2.1 - 19 km WSW of Volcano, Hawaii"
      },
      "geometry": {
        "type": "Point",
        "coordinates": [
          -155.412170410156,
          19.3956661224365,
          5.78999996185303
        ]
      },
      "id": "hv74908306"
    },
    {
      "type": "Feature",
      "properties": {
        "mag": 2.06,
        "place": "13 km ENE of Pāhala, Hawaii",
        "time": 1772003371660,
        "updated": 1772003587160,
        "tz": null,
        "url": "https://earthquake.usgs.gov/earthquakes/eventpage/hv74908291",
        "detail": "https://earthquake.usgs.gov/earthquakes/feed/v1.0/detail/hv74908291.geojson",
        "felt": null,
        "cdi": null,
        "mmi": null,
        "alert": null,
        "status": "automatic",
        "tsunami": 0,
        "sig": 65,
        "net": "hv",
        "code": "74908291",
        "ids": ",hv74908291,",
        "sources": ",hv,",
        "types": ",origin,phase-data,",
        "nst": 15,
        "dmin": 0.04115,
        "rms": 0.100000001,
        "gap": 206,
        "magType": "ml",
        "type": "earthquake",
        "title": "M 2.1 - 13 km ENE of Pāhala, Hawaii"
      },
      "geometry": {
        "type": "Point",
        "coordinates": [
          -155.357330322266,
          19.2534999847412,
          29.25
        ]
      },
      "id": "hv74908291"
    },
    {
      "type": "Feature",
      "properties": {
        "mag": 1.7,
        "place": "3 km WNW of Tyonek, Alaska",
        "time": 1772003364271,
        "updated": 1772003486294,
        "tz": null,
        "url": "https://earthquake.usgs.gov/earthquakes/eventpage/aka2026dxnelm",
        "detail": "https://earthquake.usgs.gov/earthquakes/feed/v1.0/detail/aka2026dxnelm.geojson",
        "felt": null,
        "cdi": null,
        "mmi": null,
        "alert": null,
        "status": "automatic",
        "tsunami": 0,
        "sig": 44,
        "net": "ak",
        "code": "a2026dxnelm",
        "ids": ",aka2026dxnelm,",
        "sources": ",ak,",
        "types": ",origin,phase-data,",
        "nst": 25,
        "dmin": 0.4,
        "rms": 0.6,
        "gap": 56,
        "magType": "ml",
        "type": "earthquake",
        "title": "M 1.7 - 3 km WNW of Tyonek, Alaska"
      },
      "geometry": {
        "type": "Point",
        "coordinates": [
          -151.196,
          61.079,
          9.4
        ]
      },
      "id": "aka2026dxnelm"
    },
    {
      "type": "Feature",
      "properties": {
        "mag": 2.55,
        "place": "3 km ENE of Magas Arriba, Puerto Rico",
        "time": 1772002659660,
        "updated": 1772004254740,
        "tz": null,
        "url": "https://earthquake.usgs.gov/earthquakes/eventpage/pr71508643",
        "detail": "https://earthquake.usgs.gov/earthquakes/feed/v1.0/detail/pr71508643.geojson",
        "felt": null,
        "cdi": null,
        "mmi": null,
        "alert": null,
        "status": "reviewed",
        "tsunami": 0,
        "sig": 100,
        "net": "pr",
        "code": "71508643",
        "ids": ",pr71508643,",
        "sources": ",pr,",
        "types": ",origin,phase-data,",
        "nst": 16,
        "dmin": 0.1251,
        "rms": 0.2,
        "gap": 124,
        "magType": "md",
        "type": "earthquake",
        "title": "M 2.6 - 3 km ENE of Magas Arriba, Puerto Rico"
      },
      "geometry": {
        "type": "Point",
        "coordinates": [
          -66.7365,
          18.0255,
          12.29
        ]
      },
      "id": "pr71508643"
    },
    {
      "type": "Feature",
      "properties": {
        "mag": 1.7,
        "place": "49 km NW of Toyah, Texas",
        "time": 1772002394928,
        "updated": 1772002835188,
        "tz": null,
        "url": "https://earthquake.usgs.gov/earthquakes/eventpage/tx2026dxmqne",
        "detail": "https://earthquake.usgs.gov/earthquakes/feed/v1.0/detail/tx2026dxmqne.geojson",
        "felt": null,
        "cdi": null,
        "mmi": null,
        "alert": null,
        "status": "automatic",
        "tsunami": 0,
        "sig": 44,
        "net": "tx",
        "code": "2026dxmqne",
        "ids": ",tx2026dxmqne,",
        "sources": ",tx,",
        "types": ",origin,phase-data,",
        "nst": 32,
        "dmin": 0.1,
        "rms": 0.3,
        "gap": 49,
        "magType": "ml",
        "type": "earthquake",
        "title": "M 1.7 - 49 km NW of Toyah, Texas"
      },
      "geometry": {
        "type": "Point",
        "coordinates": [
          -104.132,
          31.658,
          3.8777
        ]
      },
      "id": "tx2026dxmqne"
    }
  ],
  "bbox": [
    -155.41217041016,
    18.0255,
    3.8777,
    -66.7365,
    61.079,
    29.25
  ]
}
